aaa123123tt/__init__.py
aaa123123tt/nutellaRequests.py
aaa123123tt/nutellaSdk.py
aaa123123tt-0.1.0.dist-info/LICENSE
aaa123123tt-0.1.0.dist-info/METADATA
aaa123123tt-0.1.0.dist-info/WHEEL
aaa123123tt-0.1.0.dist-info/top_level.txt
aaa123123tt-0.1.0.dist-info/RECORD
