Metadata-Version: 2.1
Name: aaa123123tt
Version: 0.1.0
Summary: for service
Home-page: UNKNOWN
Author: songpie
Author-email: songmi.ohh@gmail.com
License: MIT
Keywords: test
Platform: UNKNOWN
Classifier: Programming Language :: Python :: 3
Classifier: Programming Language :: Python :: 3.2
Classifier: Programming Language :: Python :: 3.3
Classifier: Programming Language :: Python :: 3.4
Classifier: Programming Language :: Python :: 3.5
Classifier: Programming Language :: Python :: 3.6
Classifier: Programming Language :: Python :: 3.7
Requires-Python: >=3
